fym/__init__.py
fym/_version.py
fym/config.py
fym/core.py
fym/logging.py
fym/parser.py
fym/plotting.py
fym/agents/LQR.py
fym/agents/PID.py
fym/agents/__init__.py
fym/envs/__init__.py
fym/envs/cmrac.py
fym/envs/dynamic_soaring.py
fym/envs/quadrotor_hovering.py
fym/envs/stationary_target_interception.py
fym/envs/two_wheels_robot_pathplanning.py
fym/models/__init__.py
fym/models/aircraft.py
fym/models/missile.py
fym/models/quadrotor.py
fym/models/two_wheels_robot.py
fym/utils/__init__.py
fym/utils/linearization.py
fym/utils/rot.py
fym-1.3.0.dist-info/LICENSE
fym-1.3.0.dist-info/METADATA
fym-1.3.0.dist-info/WHEEL
fym-1.3.0.dist-info/top_level.txt
fym-1.3.0.dist-info/RECORD
