Metadata-Version: 2.1
Name: fym
Version: 1.3.0
Summary: Fym: An object-oriented simulator for dynamic systems
Home-page: https://github.com/seong-hun/fym
Author: Seong-hun Kim
Author-email: kshoon92@gmail.com
Classifier: Programming Language :: Python :: 3
Classifier: License :: OSI Approved :: MIT License
Classifier: Operating System :: OS Independent
Requires-Python: >=3.7
License-File: LICENSE
Requires-Dist: numpy
Requires-Dist: scipy
Requires-Dist: matplotlib
Requires-Dist: numdifftools
Requires-Dist: h5py
Requires-Dist: tqdm
